gumnut_server/__init__.py
gumnut_server/server.py
gumnut_server/websocket.py
gumnut_server-1.0.0rc1.dist-info/LICENSE
gumnut_server-1.0.0rc1.dist-info/METADATA
gumnut_server-1.0.0rc1.dist-info/WHEEL
gumnut_server-1.0.0rc1.dist-info/entry_points.txt
gumnut_server-1.0.0rc1.dist-info/top_level.txt
gumnut_server-1.0.0rc1.dist-info/RECORD
